alu.vhd
-- <Your name here>
-- CS 232 Spring 2013
library ieee;
use ieee.std_logic_1164.all;
use ieee.numeric_std.all;

-- The alu circuit implements the specified operation on srcA and srcB, putting
-- the result in dest and setting the appropriate condition flags.

-- The opcode meanings are shown in the case statement below

-- condition outputs
-- cr(0) <= '1' if the result of the operation is 0
-- cr(1) <= '1' if there is a 2's complement overflow
-- cr(2) <= '1' if the result of the operation is negative
-- cr(3) <= '1' if the operation generated a carry of '1'

-- Note that the and/or/xor operations are defined on std_logic_vectors, so you
-- may have to convert the srcA and srcB signals to std_logic_vectors, execute
-- the operation, and then convert the result back to an unsigned.  You can do
-- this all within a single expression.


entity alu is
  
  port (
    srcA : in  unsigned(15 downto 0);         -- input A
    srcB : in  unsigned(15 downto 0);         -- input B
    op   : in  std_logic_vector(2 downto 0);  -- operation
    cr   : out std_logic_vector(3 downto 0);  -- condition outputs
    dest : out unsigned(15 downto 0));        -- output value

end alu;

architecture test of alu is

  -- The signal tdest is an intermediate signal to hold the result and
  -- catch the carry bit in location 16.
  signal tdest : unsigned(16 downto 0);  
  
  -- Note that you should always put the carry bit into index 16, even if the
  -- carry is shifted out the right side of the number (into position -1) in
  -- the case of a shift or rotate operation.  This makes it easy to set the
  -- condition flag in the case of a carry out.

begin  -- test
  process (srcA, srcB, op)
  begin  -- process
    case op is
      when "000" =>   
			
			tdest <= (srcA(15) & srcA) + (srcB(15) & srcB); -- addition     tdest = srcA + srcB
		
      when "001" =>  
						
			tdest <= (srcA(15) & srcA) - (srcB(15) & srcB); -- subtraction  tdest = srcA - srcB
      
      when "010" => 
		
			tdest <= '0' & (srcA and srcB); -- and          tdest = srcA and srcB
		
      when "011" =>  
			
			tdest <= '0' & (srcA or srcB);  -- or           tdest = srcA or srcB
     
      when "100" => 
			
			tdest <= '0' & (srcA xor srcB); -- xor          tdest = srcA xor srcB
		
      when "101" =>  
			if srcB(0) = '0' then
				tdest <= srcA &'0';
			else	
			tdest <= srcA(0) & srcA(15) & srcA(15 downto 1);  -- shift        tdest = srcA shifted left by one if srcB(0) is 0, otherwise arithmetic shifted right
		end if;
     
      when "110" =>   
			if srcB(0) = '0' then
				tdest <= srcA(15) & srcA(14 downto 0) & srcA(15);
			else
				tdest <= srcA(0) & srcA(0) & srcA(15 downto 1);-- rotate       tdest = srcA rotated left by one if srcB(0) is 0, otherwise right
			end if;
      when "111" =>  
			tdest <= '0' & srcA; -- pass         tdest = srcA
      when others =>
        null;
    end case;
  end process;
  
  process(tdest)
  begin
  if tdest(15 downto 0) = x"0000" then
	cr(0) <= '1';
  else
   cr(0) <='0';
  end if;
  
  if (op = "000" or op = "001") and tdest(15) /= srcA(15) and srcA(15) = srcB(15)
  then
    cr(1) <= '1';
  else
    cr(1) <= '0';	
  end if; 
  
  if tdest(15) = '1' then
	cr(2) <= '1';
  else
	cr(2) <= '0';
  end if;
  
  if tdest(16) = '1' then
	cr(3) <= '1';
  else
	cr(3) <= '0';
  end if;
end process;

  -- connect the low 16 bits of tdest to dest here
  dest <= tdest(15 downto 0);

end test;

alutestbench.vhd
library ieee;
use ieee.std_logic_1164.all;
use ieee.numeric_std.all;

entity alutestbench is
end alutestbench;

architecture test of alutestbench is
  constant num_cycles : integer := 20;

  
  signal state: unsigned(3 downto 0);
  signal srcA: unsigned(15 downto 0);
  signal srcB: unsigned(15 downto 0);
  signal dest: unsigned(15 downto 0) := "0000000000000000";
  signal opcode: std_logic_vector(2 downto 0);

  signal output: std_logic_vector(15 downto 0) := "0000000000000000";
  signal CR: std_logic_vector(3 downto 0) := "0000";
  signal clk: std_logic := '1';
  signal reset: std_logic;
  
  -- component statement for the ALU
  component alu
    port (
      srcA : in  unsigned(15 downto 0);         -- input A
      srcB : in  unsigned(15 downto 0);         -- input B
      op   : in  std_logic_vector(2 downto 0);  -- operation
      cr   : out std_logic_vector(3 downto 0);  -- condition outputs
      dest : out unsigned(15 downto 0));        -- output value
  end component;
  
begin

  -- start off with a short reset
  reset <= '0', '1' after 1 ns;

  -- create a clock
  process
  begin
    for i in 1 to num_cycles loop
      clk <= not clk;
      wait for 1 ns;
      clk <= not clk;
      wait for 1 ns;
    end loop;
    wait;
  end process;
  

  aluinstance: alu
    port map( srcA => srcA, srcB => srcB, dest => dest, op => opcode, cr => CR );

  output <= std_logic_vector(dest); -- connect dest and the output

  process(clk, reset)
  begin 
    if reset = '0' then
      srcA <= "0000000000000000";
      srcB <= "0000000000000000";
      state <= "0000";
    elsif rising_edge(clk) then
      case state is
        when "0000" =>
          srcA <= x"7FFF";
          srcB <= x"0002";
          opcode <= "000"; -- addition, answer should be x8001, flags "0110"
          state <= state + 1;
        when "0001" =>
          srcA <= x"FF10";
          srcB <= x"FFFF";
          opcode <= "000"; -- addition, answer should be xFF0F, flags "1100"
          state <= state + 1;
        when "0010" =>
          srcA <= x"0014";
          srcB <= x"0012";
          opcode <= "001"; -- subtraction, answer should be x0002, flags "0000"
          state <= state + 1;
        when "0011" =>
          srcA <= x"FFFE";
          srcB <= x"FFFF";
          opcode <= "001"; -- subtraction, answer should be xFFFF, flags "1100"
          state <= state + 1;
        when "0100" =>
          srcA <= x"FFFF";
          srcB <= x"AAAA";
          opcode <= "010"; -- and, answer should be xAAAA, flags "0100"
          state <= state + 1;
        when "0101" =>
          srcA <= x"00FF";
          srcB <= x"AAAA"; -- and, answer should be x00AA, flags "0000"
          opcode <= "010";
          state <= state + 1;
        when "0110" =>
          srcA <= x"FFFF";
          srcB <= x"AAAA";
          opcode <= "011"; -- or, answer should be xFFFF, flags "0100"
          state <= state + 1;
        when "0111" =>
          srcA <= x"FF00";
          srcB <= x"AAAA"; -- or, answer should be xFFAA, flags "0100"
          opcode <= "011";
          state <= state + 1;
        when "1000" =>
          srcA <= x"FFFF";
          srcB <= x"AAAA";
          opcode <= "100"; -- xor, answer should be x5555, flags "0000"
          state <= state + 1;
        when "1001" =>
          srcA <= x"FF00";
          srcB <= x"AAAA";
          opcode <= "100"; -- xor, answer should be x55AA, flags "0000"
          state <= state + 1;
        when "1010" =>
          srcA <= x"AAAA";
          srcB <= x"0000";
          opcode <= "101"; -- shift, left by 1, answer should be x5554, flags "1000"
          state <= state + 1;
        when "1011" =>
          srcA <= x"AAAA";
          srcB <= x"0001";
          opcode <= "101"; -- shift, right by 1, answer should be xD555, flags "0100"
          state <= state + 1;
        when "1100" =>
          srcA <= x"AAAA";
          srcB <= x"0000";
          opcode <= "110"; -- rotate, left by 1, answer should be x5555, flags "1000"
          state <= state + 1;
        when "1101" =>
          srcA <= x"AAAA";
          srcB <= x"0001";
          opcode <= "110"; -- rotate, right by 1, answer should be x5555, flags "0000"
          state <= state + 1;
        when "1110" =>
          srcA <= x"0000";
          srcB <= x"0234";
          opcode <= "111"; -- pass through, answer should be x0000, flags "0001"
          state <= state + 1;
        when others =>
          srcA <= x"F012";
          srcB <= x"0000";
          opcode <= "111"; -- pass through, answer should be xF012, flags "0100"
          state <= state + 1;
      end case;
    end if;
  end process;

end test;

alutestbench.vcd
$date
  Mon Nov 27 14:40:14 2023
$end
$version
  GHDL v0
$end
$timescale
  1 fs
$end
$scope module standard $end
$upscope $end
$scope module std_logic_1164 $end
$upscope $end
$scope module numeric_std $end
$upscope $end
$scope module alutestbench $end
$var reg 4 ! state[3:0] $end
$var reg 16 " srca[15:0] $end
$var reg 16 # srcb[15:0] $end
$var reg 16 $ dest[15:0] $end
$var reg 3 % opcode[2:0] $end
$var reg 16 & output[15:0] $end
$var reg 4 ' cr[3:0] $end
$var reg 1 ( clk $end
$var reg 1 ) reset $end
$scope module aluinstance $end
$var reg 16 * srca[15:0] $end
$var reg 16 + srcb[15:0] $end
$var reg 3 , op[2:0] $end
$var reg 4 - cr[3:0] $end
$var reg 16 . dest[15:0] $end
$var reg 17 / tdest[16:0] $end
$upscope $end
$upscope $end
$enddefinitions $end
#0
b0000 !
b0000000000000000 "
b0000000000000000 #
bUUUUUUUUUUUUUUUU $
bUUU %
bUUUUUUUUUUUUUUUU &
b0000 '
0(
0)
b0000000000000000 *
b0000000000000000 +
bUUU ,
b0000 -
bUUUUUUUUUUUUUUUU .
bUUUUUUUUUUUUUUUUU /
#1000000
b0001 !
b0111111111111111 "
b0000000000000010 #
b1000000000000001 $
b000 %
b1000000000000001 &
b0110 '
1(
1)
b0111111111111111 *
b0000000000000010 +
b000 ,
b0110 -
b1000000000000001 .
b01000000000000001 /
#2000000
0(
#3000000
b0010 !
b1111111100010000 "
b1111111111111111 #
b1111111100001111 $
b1111111100001111 &
b1100 '
1(
b1111111100010000 *
b1111111111111111 +
b1100 -
b1111111100001111 .
b11111111100001111 /
#4000000
0(
#5000000
b0011 !
b0000000000010100 "
b0000000000010010 #
b0000000000000010 $
b001 %
b0000000000000010 &
b0000 '
1(
b0000000000010100 *
b0000000000010010 +
b001 ,
b0000 -
b0000000000000010 .
b00000000000000010 /
#6000000
0(
#7000000
b0100 !
b1111111111111110 "
b1111111111111111 #
b1111111111111111 $
b1111111111111111 &
b1100 '
1(
b1111111111111110 *
b1111111111111111 +
b1100 -
b1111111111111111 .
b11111111111111111 /
#8000000
0(
#9000000
b0101 !
b1111111111111111 "
b1010101010101010 #
b1010101010101010 $
b010 %
b1010101010101010 &
b0100 '
1(
b1111111111111111 *
b1010101010101010 +
b010 ,
b0100 -
b1010101010101010 .
b01010101010101010 /
#10000000
0(
#11000000
b0110 !
b0000000011111111 "
b0000000010101010 $
b0000000010101010 &
b0000 '
1(
b0000000011111111 *
b0000 -
b0000000010101010 .
b00000000010101010 /
#12000000
0(
#13000000
b0111 !
b1111111111111111 "
b1111111111111111 $
b011 %
b1111111111111111 &
b0100 '
1(
b1111111111111111 *
b011 ,
b0100 -
b1111111111111111 .
b01111111111111111 /
#14000000
0(
#15000000
b1000 !
b1111111100000000 "
b1111111110101010 $
b1111111110101010 &
1(
b1111111100000000 *
b1111111110101010 .
b01111111110101010 /
#16000000
0(
#17000000
b1001 !
b1111111111111111 "
b0101010101010101 $
b100 %
b0101010101010101 &
b0000 '
1(
b1111111111111111 *
b100 ,
b0000 -
b0101010101010101 .
b00101010101010101 /
#18000000
0(
#19000000
b1010 !
b1111111100000000 "
b0101010110101010 $
b0101010110101010 &
1(
b1111111100000000 *
b0101010110101010 .
b00101010110101010 /
#20000000
0(
#21000000
b1011 !
b1010101010101010 "
b0000000000000000 #
b0101010101010100 $
b101 %
b0101010101010100 &
b1000 '
1(
b1010101010101010 *
b0000000000000000 +
b101 ,
b1000 -
b0101010101010100 .
b10101010101010100 /
#22000000
0(
#23000000
b1100 !
b0000000000000001 #
b1101010101010101 $
b1101010101010101 &
b0100 '
1(
b0000000000000001 +
b0100 -
b1101010101010101 .
b01101010101010101 /
#24000000
0(
#25000000
b1101 !
b0000000000000000 #
b0101010101010101 $
b110 %
b0101010101010101 &
b1000 '
1(
b0000000000000000 +
b110 ,
b1000 -
b0101010101010101 .
b10101010101010101 /
#26000000
0(
#27000000
b1110 !
b0000000000000001 #
b0000 '
1(
b0000000000000001 +
b0000 -
b00101010101010101 /
#28000000
0(
#29000000
b1111 !
b0000000000000000 "
b0000001000110100 #
b0000000000000000 $
b111 %
b0000000000000000 &
b0001 '
1(
b0000000000000000 *
b0000001000110100 +
b111 ,
b0001 -
b0000000000000000 .
b00000000000000000 /
#30000000
0(
#31000000
b0000 !
b1111000000010010 "
b0000000000000000 #
b1111000000010010 $
b1111000000010010 &
b0100 '
1(
b1111000000010010 *
b0000000000000000 +
b0100 -
b1111000000010010 .
b01111000000010010 /
#32000000
0(
#33000000
b0001 !
b0111111111111111 "
b0000000000000010 #
b1000000000000001 $
b000 %
b1000000000000001 &
b0110 '
1(
b0111111111111111 *
b0000000000000010 +
b000 ,
b0110 -
b1000000000000001 .
b01000000000000001 /
#34000000
0(
#35000000
b0010 !
b1111111100010000 "
b1111111111111111 #
b1111111100001111 $
b1111111100001111 &
b1100 '
1(
b1111111100010000 *
b1111111111111111 +
b1100 -
b1111111100001111 .
b11111111100001111 /
#36000000
0(
#37000000
b0011 !
b0000000000010100 "
b0000000000010010 #
b0000000000000010 $
b001 %
b0000000000000010 &
b0000 '
1(
b0000000000010100 *
b0000000000010010 +
b001 ,
b0000 -
b0000000000000010 .
b00000000000000010 /
#38000000
0(
#39000000
b0100 !
b1111111111111110 "
b1111111111111111 #
b1111111111111111 $
b1111111111111111 &
b1100 '
1(
b1111111111111110 *
b1111111111111111 +
b1100 -
b1111111111111111 .
b11111111111111111 /
